demessaging/NetCDFDecoder.py
demessaging/PulsarConnection.py
demessaging/PulsarMessageConstants.py
demessaging/PulsarMessageConsumer.py
demessaging/PulsarMessageProducer.py
demessaging/__init__.py
demessaging/__main__.py
demessaging/_version.py
demessaging/cli.py
demessaging/py.typed
demessaging/template.py
demessaging/utils.py
demessaging/backend/__init__.py
demessaging/backend/class_.py
demessaging/backend/function.py
demessaging/backend/module.py
demessaging/backend/utils.py
demessaging/config/__init__.py
demessaging/config/api.py
demessaging/config/backend.py
demessaging/config/logging.py
demessaging/config/logging.yaml
demessaging/config/messaging.py
demessaging/config/registry.py
demessaging/messaging/__init__.py
demessaging/messaging/connection.py
demessaging/messaging/constants.py
demessaging/messaging/consumer.py
demessaging/messaging/producer.py
demessaging/serializers/__init__.py
demessaging/serializers/xarray.py
demessaging/templates/class_.py.jinja2
demessaging/templates/function.py.jinja2
demessaging/templates/module.py.jinja2
demessaging/validators/__init__.py
demessaging/validators/xarray.py
demessaging-0.6.4.dist-info/licenses/LICENSES/Apache-2.0.txt
demessaging-0.6.4.dist-info/licenses/LICENSES/CC-BY-4.0.txt
demessaging-0.6.4.dist-info/licenses/LICENSES/CC0-1.0.txt
demessaging-0.6.4.dist-info/METADATA
demessaging-0.6.4.dist-info/WHEEL
demessaging-0.6.4.dist-info/entry_points.txt
demessaging-0.6.4.dist-info/top_level.txt
demessaging-0.6.4.dist-info/RECORD
