Metadata-Version: 2.4
Name: demessaging
Version: 0.6.4
Summary: python module wrapper for the data analytics software framework DASF
Author: Mike Sips, Doris Dransch
Author-email: Daniel Eggert <daniel.eggert@gfz-potsdam.de>, "Philipp S. Sommer" <philipp.sommer@hereon.de>
Maintainer-email: "Philipp S. Sommer" <philipp.sommer@hereon.de>
Project-URL: Homepage, https://codebase.helmholtz.cloud/dasf/dasf-messaging-python
Project-URL: Documentation, https://dasf.readthedocs.io/en/latest/
Project-URL: Source, https://codebase.helmholtz.cloud/dasf/dasf-messaging-python
Project-URL: Tracker, https://codebase.helmholtz.cloud/dasf/dasf-messaging-python/issues/
Keywords: digital-earth,dasf,pulsar,gfz,hzg,hereon,hgf,helmholtz,remote procedure call,rpc,django,python,websocket
Classifier: Development Status :: 4 - Beta
Classifier: Intended Audience :: Developers
Classifier: Operating System :: OS Independent
Classifier: Programming Language :: Python
Classifier: Programming Language :: Python :: 3
Classifier: Programming Language :: Python :: 3 :: Only
Classifier: Programming Language :: Python :: 3.9
Classifier: Programming Language :: Python :: 3.10
Classifier: Programming Language :: Python :: 3.11
Classifier: Programming Language :: Python :: 3.12
Classifier: Programming Language :: Python :: 3.11
Classifier: Programming Language :: Python :: 3.12
Classifier: Programming Language :: Python :: 3.13
Classifier: Programming Language :: Python :: 3.14
Classifier: Typing :: Typed
Requires-Python: >=3.7
License-File: LICENSES/Apache-2.0.txt
License-File: LICENSES/CC-BY-4.0.txt
License-File: LICENSES/CC0-1.0.txt
Requires-Dist: websocket-client<1.8,>=1.5
Requires-Dist: docstring_parser<0.16
Requires-Dist: pydantic<3.0,>=2.2
Requires-Dist: pydantic-settings
Requires-Dist: typing_extensions
Requires-Dist: jinja2>=3.1.2
Requires-Dist: deprogressapi>=0.3.0
Requires-Dist: PyYAML>=4.2b
Provides-Extra: backend
Requires-Dist: isort>=5.10.1; extra == "backend"
Requires-Dist: black>=22.3.0; extra == "backend"
Requires-Dist: autoflake>=2.0.0; extra == "backend"
Provides-Extra: testsite
Requires-Dist: demessaging[backend]; extra == "testsite"
Requires-Dist: tox; extra == "testsite"
Requires-Dist: isort==7.0.0; extra == "testsite"
Requires-Dist: black==25.9.0; extra == "testsite"
Requires-Dist: blackdoc==0.4.5; extra == "testsite"
Requires-Dist: flake8==7.3.0; extra == "testsite"
Requires-Dist: pre-commit; extra == "testsite"
Requires-Dist: mypy==1.18.2; extra == "testsite"
Requires-Dist: dasf-broker-django>=0.0.1.dev0; extra == "testsite"
Requires-Dist: types-PyYAML; extra == "testsite"
Requires-Dist: daphne; extra == "testsite"
Requires-Dist: django-rest-framework; extra == "testsite"
Requires-Dist: djangorestframework; extra == "testsite"
Requires-Dist: pytest-django; extra == "testsite"
Requires-Dist: pytest-cov; extra == "testsite"
Requires-Dist: reuse==6.1.2; extra == "testsite"
Requires-Dist: xarray; sys_platform != "win32" and extra == "testsite"
Requires-Dist: scipy; sys_platform != "win32" and extra == "testsite"
Requires-Dist: cffconvert; extra == "testsite"
Provides-Extra: docs
Requires-Dist: autodocsumm; extra == "docs"
Requires-Dist: sphinx-rtd-theme; extra == "docs"
Requires-Dist: hereon-netcdf-sphinxext; extra == "docs"
Requires-Dist: sphinx-argparse; extra == "docs"
Requires-Dist: sphinx-design; extra == "docs"
Requires-Dist: myst_parser; extra == "docs"
Provides-Extra: dev
Requires-Dist: demessaging[testsite]; extra == "dev"
Requires-Dist: demessaging[docs]; extra == "dev"
Requires-Dist: reuse-shortcuts>=1.0.1; extra == "dev"
Requires-Dist: types-PyYAML; extra == "dev"
Dynamic: license-file
